pygame_canvas/__init__.py
pygame_canvas/main.py
pygame_canvas/pygame_canvas.py
pygame_canvas-1.7.0.dist-info/METADATA
pygame_canvas-1.7.0.dist-info/WHEEL
pygame_canvas-1.7.0.dist-info/top_level.txt
pygame_canvas-1.7.0.dist-info/RECORD
