Metadata-Version: 2.1
Name: pygame_canvas
Version: 1.7.0
Summary: A library for canvas operations using pygame
Home-page: https://x.com/gioseaxmc
Requires-Python: >=3.6
Requires-Dist: pygame-ce
